{"name":"CATEGORY-EDUCATION-CN","rules":[{"type":"full","value":"moocs.unipus.cn","attrs":[]},{"type":"full","value":"opencourse.pku.edu.cn","attrs":[]},{"type":"full","value":"study.163.com","attrs":[]},{"type":"domain","value":"ketangpai.com","attrs":[]},{"type":"domain","value":"rainclassroom.com","attrs":[]},{"type":"domain","value":"chesicc.com","attrs":[]},{"type":"domain","value":"cedf.cn","attrs":[]},{"type":"domain","value":"chsi.cn","attrs":[]},{"type":"domain","value":"gfbzb.cn","attrs":[]},{"type":"domain","value":"pmphmooc.com","attrs":[]},{"type":"domain","value":"openlearning.com","attrs":[]},{"type":"domain","value":"mooc.cn","attrs":[]},{"type":"domain","value":"icourses.cn","attrs":[]},{"type":"domain","value":"icourse163.org","attrs":[]},{"type":"domain","value":"cnmooc.org","attrs":[]},{"type":"domain","value":"chinesemooc.org","attrs":[]},{"type":"domain","value":"yuketang.cn","attrs":[]},{"type":"domain","value":"gfbzb.com","attrs":[]},{"type":"domain","value":"pigai.org","attrs":[]},{"type":"domain","value":"zhihuishu.com","attrs":[]},{"type":"domain","value":"fenbilantian.com","attrs":[]},{"type":"domain","value":"gfbzb.net","attrs":[]},{"type":"domain","value":"ncss.cn","attrs":[]},{"type":"domain","value":"fenbilantian.cn","attrs":[]},{"type":"domain","value":"fenbike.com","attrs":[]},{"type":"domain","value":"fenbike.cn","attrs":[]},{"type":"domain","value":"qgzb.net","attrs":[]},{"type":"domain","value":"fenbi.com","attrs":[]},{"type":"domain","value":"zbbm.net","attrs":[]},{"type":"domain","value":"yudou.cn","attrs":[]},{"type":"domain","value":"yushiyan.net","attrs":[]},{"type":"domain","value":"xuetangx.com","attrs":[]},{"type":"domain","value":"x-cloud.cc","attrs":[]},{"type":"domain","value":"xkw.com","attrs":[]},{"type":"domain","value":"zxxk.com","attrs":[]},{"type":"domain","value":"dearedu.com","attrs":[]},{"type":"domain","value":"kuaiduizuoye.com","attrs":[]},{"type":"domain","value":"liulishuo.com","attrs":[]},{"type":"domain","value":"llsapp.com","attrs":[]},{"type":"domain","value":"llscdn.com","attrs":[]},{"type":"domain","value":"llsserver.com","attrs":[]},{"type":"domain","value":"baicizhan.com","attrs":[]},{"type":"domain","value":"baicizhan.org","attrs":[]},{"type":"domain","value":"bczcdn.com","attrs":[]},{"type":"domain","value":"bczeducation.cn","attrs":[]},{"type":"domain","value":"zhan.com","attrs":[]},{"type":"domain","value":"burningvocabulary.cn","attrs":[]},{"type":"domain","value":"burningvocabulary.com","attrs":[]},{"type":"domain","value":"dgjy.net","attrs":[]},{"type":"domain","value":"91yunxiao.com","attrs":[]},{"type":"domain","value":"aiyunxiao.com","attrs":[]},{"type":"domain","value":"haofenshu.com","attrs":[]},{"type":"domain","value":"iyunxiao.com","attrs":[]},{"type":"domain","value":"yunxiao.com","attrs":[]},{"type":"domain","value":"keboyunxiao.com","attrs":[]},{"type":"domain","value":"chesicc.net","attrs":[]},{"type":"domain","value":"chesicc.cn","attrs":[]},{"type":"domain","value":"yuanfudao.com","attrs":[]},{"type":"domain","value":"magedu.com","attrs":[]},{"type":"domain","value":"oldboyedu.com","attrs":[]},{"type":"domain","value":"eduei.com","attrs":[]},{"type":"domain","value":"edu.cn","attrs":[]},{"type":"domain","value":"ystbds.com","attrs":[]},{"type":"domain","value":"neoscholar.com","attrs":[]},{"type":"domain","value":"neoschool.com","attrs":[]},{"type":"domain","value":"winyoungreading.com","attrs":[]},{"type":"domain","value":"hugecore.net","attrs":[]},{"type":"domain","value":"shareintelli.com","attrs":[]},{"type":"domain","value":"mojidict.com","attrs":[]},{"type":"domain","value":"cctalk.com","attrs":[]},{"type":"domain","value":"hjapi.com","attrs":[]},{"type":"domain","value":"hjfile.cn","attrs":[]},{"type":"domain","value":"hujiang.com","attrs":[]},{"type":"domain","value":"yeshj.com","attrs":[]},{"type":"domain","value":"17zuoye.cn","attrs":[]},{"type":"domain","value":"17zuoye.com","attrs":[]},{"type":"domain","value":"17zuoye.net","attrs":[]},{"type":"domain","value":"applysquare.com","attrs":[]},{"type":"domain","value":"applysquare.net","attrs":[]},{"type":"domain","value":"koocdn.com","attrs":[]},{"type":"domain","value":"koolearn.com","attrs":[]},{"type":"domain","value":"koopass.com","attrs":[]},{"type":"domain","value":"baydn.com","attrs":[]},{"type":"domain","value":"shanbay.com","attrs":[]},{"type":"domain","value":"speiyou.com","attrs":[]},{"type":"domain","value":"xesimg.com","attrs":[]},{"type":"domain","value":"xueersi.com","attrs":[]},{"type":"domain","value":"banmaaike.com","attrs":[]},{"type":"domain","value":"xiaoyuankousuan.com","attrs":[]},{"type":"domain","value":"ybccode.com","attrs":[]},{"type":"domain","value":"weilaiyunxiao.com","attrs":[]},{"type":"domain","value":"yuansouti.com","attrs":[]},{"type":"domain","value":"yuantiku.com","attrs":[]},{"type":"domain","value":"fbstatic.cn","attrs":[]},{"type":"domain","value":"ncss.org.cn","attrs":[]},{"type":"domain","value":"chesicc.org.cn","attrs":[]},{"type":"domain","value":"qgzb.com.cn","attrs":[]},{"type":"domain","value":"chinayz.com.cn","attrs":[]},{"type":"domain","value":"zbbm.gov.cn","attrs":[]},{"type":"domain","value":"gfbzb.com.cn","attrs":[]},{"type":"domain","value":"chsi.com.cn","attrs":[]},{"type":"domain","value":"qgzb.gov.cn","attrs":[]},{"type":"domain","value":"gfbzb.gov.cn","attrs":[]},{"type":"domain","value":"gatzs.com.cn","attrs":[]},{"type":"domain","value":"chesicc.net.cn","attrs":[]},{"type":"domain","value":"chesicc.com.cn","attrs":[]},{"type":"domain","value":"chei.com.cn","attrs":[]},{"type":"domain","value":"chdi.com.cn","attrs":[]},{"type":"domain","value":"cedf.org.cn","attrs":[]},{"type":"domain","value":"icve.com.cn","attrs":[]}]}
