{"name":"CATEGORY-MOBILE-REPAIR","rules":[{"type":"domain","value":"androidfilehost.com","attrs":[]},{"type":"domain","value":"unlocktool.net","attrs":[]},{"type":"domain","value":"borneo.world","attrs":[]},{"type":"domain","value":"borneoasia.com","attrs":[]},{"type":"domain","value":"borneoschematic.com","attrs":[]},{"type":"domain","value":"bosharso.net","attrs":[]},{"type":"domain","value":"hostborneo.org","attrs":[]},{"type":"domain","value":"easy-jtag.com","attrs":[]},{"type":"domain","value":"z3x-team.com","attrs":[]}]}
