{"name":"DAILYMAIL","rules":[{"type":"domain","value":"mailonsunday.ie","attrs":[]},{"type":"domain","value":"dailym.ai","attrs":[]},{"type":"domain","value":"mailhealth.com","attrs":[]},{"type":"domain","value":"dailymail.com","attrs":[]},{"type":"domain","value":"thismon.ee","attrs":[]},{"type":"domain","value":"dailymail.dk","attrs":[]},{"type":"domain","value":"dailymailonline.com","attrs":[]},{"type":"domain","value":"mailonline.com","attrs":[]},{"type":"domain","value":"mol.im","attrs":[]},{"type":"domain","value":"dailymail.com.au","attrs":[]},{"type":"domain","value":"dmgmediaprivacy.co.uk","attrs":[]},{"type":"domain","value":"mailonsunday.co.uk","attrs":[]},{"type":"domain","value":"anm.co.uk","attrs":[]},{"type":"domain","value":"metro.co.uk","attrs":[]},{"type":"domain","value":"dailymail.co.uk","attrs":[]},{"type":"domain","value":"thisismoney.co.uk","attrs":[]},{"type":"domain","value":"mailonline.co.uk","attrs":[]}]}
