{"name":"FOX","rules":[{"type":"domain","value":"afewmomentswith.com","attrs":[]},{"type":"domain","value":"anidom.com","attrs":[]},{"type":"domain","value":"bentobox.tv","attrs":[]},{"type":"domain","value":"casoneexchange.com","attrs":[]},{"type":"domain","value":"coronavirusnow.com","attrs":[]},{"type":"domain","value":"fox","attrs":[]},{"type":"domain","value":"fox-corporation.com","attrs":[]},{"type":"domain","value":"fox-news.com","attrs":[]},{"type":"domain","value":"fox.com","attrs":[]},{"type":"domain","value":"fox.tv","attrs":[]},{"type":"domain","value":"fox10.tv","attrs":[]},{"type":"domain","value":"fox10news.com","attrs":[]},{"type":"domain","value":"fox10phoenix.com","attrs":[]},{"type":"domain","value":"fox11.com","attrs":[]},{"type":"domain","value":"fox13memphis.com","attrs":[]},{"type":"domain","value":"fox13news.com","attrs":[]},{"type":"domain","value":"fox23.com","attrs":[]},{"type":"domain","value":"fox23maine.com","attrs":[]},{"type":"domain","value":"fox247.com","attrs":[]},{"type":"domain","value":"fox247.tv","attrs":[]},{"type":"domain","value":"fox26.com","attrs":[]},{"type":"domain","value":"fox26houston.com","attrs":[]},{"type":"domain","value":"fox28media.com","attrs":[]},{"type":"domain","value":"fox29.com","attrs":[]},{"type":"domain","value":"fox2detroit.com","attrs":[]},{"type":"domain","value":"fox2news.com","attrs":[]},{"type":"domain","value":"fox32.com","attrs":[]},{"type":"domain","value":"fox32chicago.com","attrs":[]},{"type":"domain","value":"fox35orlando.com","attrs":[]},{"type":"domain","value":"fox38corpuschristi.com","attrs":[]},{"type":"domain","value":"fox42kptm.com","attrs":[]},{"type":"domain","value":"fox46.com","attrs":[]},{"type":"domain","value":"fox46charlotte.com","attrs":[]},{"type":"domain","value":"fox47.com","attrs":[]},{"type":"domain","value":"fox49.tv","attrs":[]},{"type":"domain","value":"fox4news.com","attrs":[]},{"type":"domain","value":"fox51tns.net","attrs":[]},{"type":"domain","value":"fox5atlanta.com","attrs":[]},{"type":"domain","value":"fox5dc.com","attrs":[]},{"type":"domain","value":"fox5ny.com","attrs":[]},{"type":"domain","value":"fox5storm.com","attrs":[]},{"type":"domain","value":"fox6now.com","attrs":[]},{"type":"domain","value":"fox7.com","attrs":[]},{"type":"domain","value":"fox7austin.com","attrs":[]},{"type":"domain","value":"fox9.com","attrs":[]},{"type":"domain","value":"foxacrossamerica.com","attrs":[]},{"type":"domain","value":"foxaffiliateportal.com","attrs":[]},{"type":"domain","value":"foxandfriends.com","attrs":[]},{"type":"domain","value":"foxbet.com","attrs":[]},{"type":"domain","value":"foxbusiness.com","attrs":[]},{"type":"domain","value":"foxbusiness.tv","attrs":[]},{"type":"domain","value":"foxbusinessgo.com","attrs":[]},{"type":"domain","value":"foxcanvasroom.com","attrs":[]},{"type":"domain","value":"foxcareers.com","attrs":[]},{"type":"domain","value":"foxcharlotte.com","attrs":[]},{"type":"domain","value":"foxcincy.com","attrs":[]},{"type":"domain","value":"foxcincy.jobs","attrs":[]},{"type":"domain","value":"foxcincy.net","attrs":[]},{"type":"domain","value":"foxcollegesports.com","attrs":[]},{"type":"domain","value":"foxcorporation.com","attrs":[]},{"type":"domain","value":"foxcreativeuniversity.com","attrs":[]},{"type":"domain","value":"foxcredit.com","attrs":[]},{"type":"domain","value":"foxcredit.org","attrs":[]},{"type":"domain","value":"foxd.tv","attrs":[]},{"type":"domain","value":"foxdcg.com","attrs":[]},{"type":"domain","value":"foxdeportes.com","attrs":[]},{"type":"domain","value":"foxdeportes.net","attrs":[]},{"type":"domain","value":"foxdeportes.tv","attrs":[]},{"type":"domain","value":"foxdigitalmovies.com","attrs":[]},{"type":"domain","value":"foxdoua.com","attrs":[]},{"type":"domain","value":"foxentertainment.com","attrs":[]},{"type":"domain","value":"foxest.com","attrs":[]},{"type":"domain","value":"foxfaq.com","attrs":[]},{"type":"domain","value":"foxfdm.com","attrs":[]},{"type":"domain","value":"foxfiles.com","attrs":[]},{"type":"domain","value":"foxinc.com","attrs":[]},{"type":"domain","value":"foxkansas.com","attrs":[]},{"type":"domain","value":"foxla.com","attrs":[]},{"type":"domain","value":"foxla.tv","attrs":[]},{"type":"domain","value":"foxlexington.com","attrs":[]},{"type":"domain","value":"foxmediacloud.com","attrs":[]},{"type":"domain","value":"foxnation.com","attrs":[]},{"type":"domain","value":"foxnebraska.com","attrs":[]},{"type":"domain","value":"foxneo.com","attrs":[]},{"type":"domain","value":"foxneodigital.com","attrs":[]},{"type":"domain","value":"foxnetworks.info","attrs":[]},{"type":"domain","value":"foxnetworksinfo.com","attrs":[]},{"type":"domain","value":"foxnews.cc","attrs":[]},{"type":"domain","value":"foxnews.com","attrs":[]},{"type":"domain","value":"foxnews.net","attrs":[]},{"type":"domain","value":"foxnews.org","attrs":[]},{"type":"domain","value":"foxnews.tv","attrs":[]},{"type":"domain","value":"foxnewsaffiliates.com","attrs":[]},{"type":"domain","value":"foxnewsaroundtheworld.com","attrs":[]},{"type":"domain","value":"foxnewsb2b.com","attrs":[]},{"type":"domain","value":"foxnewschannel.com","attrs":[]},{"type":"domain","value":"foxnewsgo.net","attrs":[]},{"type":"domain","value":"foxnewsgo.org","attrs":[]},{"type":"domain","value":"foxnewsgo.tv","attrs":[]},{"type":"domain","value":"foxnewshealth.com","attrs":[]},{"type":"domain","value":"foxnewslatino.com","attrs":[]},{"type":"domain","value":"foxnewsmagazine.com","attrs":[]},{"type":"domain","value":"foxnewsnetwork.com","attrs":[]},{"type":"domain","value":"foxnewsopinion.com","attrs":[]},{"type":"domain","value":"foxnewspodcasts.com","attrs":[]},{"type":"domain","value":"foxnewspolitics.com","attrs":[]},{"type":"domain","value":"foxnewsradio.com","attrs":[]},{"type":"domain","value":"foxnewsrundown.com","attrs":[]},{"type":"domain","value":"foxnewssunday.com","attrs":[]},{"type":"domain","value":"foxon.com","attrs":[]},{"type":"domain","value":"foxphiladelphia.com","attrs":[]},{"type":"domain","value":"foxplus.com","attrs":[]},{"type":"domain","value":"foxpoker.com","attrs":[]},{"type":"domain","value":"foxrad.io","attrs":[]},{"type":"domain","value":"foxredeem.com","attrs":[]},{"type":"domain","value":"foxrelease.com","attrs":[]},{"type":"domain","value":"foxrichmond.com","attrs":[]},{"type":"domain","value":"foxrobots.com","attrs":[]},{"type":"domain","value":"foxsmallbusinesscenter.com","attrs":[]},{"type":"domain","value":"foxsmallbusinesscenter.net","attrs":[]},{"type":"domain","value":"foxsmallbusinesscenter.org","attrs":[]},{"type":"domain","value":"foxsoccer.net","attrs":[]},{"type":"domain","value":"foxsoccer.tv","attrs":[]},{"type":"domain","value":"foxsoccermatchpass.com","attrs":[]},{"type":"domain","value":"foxsoccerplus.com","attrs":[]},{"type":"domain","value":"foxsoccerplus.net","attrs":[]},{"type":"domain","value":"foxsoccerplus.tv","attrs":[]},{"type":"domain","value":"foxsoccershop.com","attrs":[]},{"type":"domain","value":"foxsports-chicago.com","attrs":[]},{"type":"domain","value":"foxsports-newyork.com","attrs":[]},{"type":"domain","value":"foxsports-world.com","attrs":[]},{"type":"domain","value":"foxsports.cl","attrs":[]},{"type":"domain","value":"foxsports.co","attrs":[]},{"type":"domain","value":"foxsports.co.ve","attrs":[]},{"type":"domain","value":"foxsports.com","attrs":[]},{"type":"domain","value":"foxsports.com.ar","attrs":[]},{"type":"domain","value":"foxsports.com.bo","attrs":[]},{"type":"domain","value":"foxsports.com.br","attrs":[]},{"type":"domain","value":"foxsports.com.co","attrs":[]},{"type":"domain","value":"foxsports.com.ec","attrs":[]},{"type":"domain","value":"foxsports.com.gt","attrs":[]},{"type":"domain","value":"foxsports.com.mx","attrs":[]},{"type":"domain","value":"foxsports.com.pe","attrs":[]},{"type":"domain","value":"foxsports.com.py","attrs":[]},{"type":"domain","value":"foxsports.com.uy","attrs":[]},{"type":"domain","value":"foxsports.com.ve","attrs":[]},{"type":"domain","value":"foxsports.gt","attrs":[]},{"type":"domain","value":"foxsports.info","attrs":[]},{"type":"domain","value":"foxsports.net","attrs":[]},{"type":"domain","value":"foxsports.net.br","attrs":[]},{"type":"domain","value":"foxsports.pe","attrs":[]},{"type":"domain","value":"foxsports.sv","attrs":[]},{"type":"domain","value":"foxsports.uy","attrs":[]},{"type":"domain","value":"foxsports2.com","attrs":[]},{"type":"domain","value":"foxsportsflorida.com","attrs":[]},{"type":"domain","value":"foxsportsgo.com","attrs":[]},{"type":"domain","value":"foxsportsla.com","attrs":[]},{"type":"domain","value":"foxsportsnetmilwaukee.com","attrs":[]},{"type":"domain","value":"foxsportsneworleans.com","attrs":[]},{"type":"domain","value":"foxsportsracing.com","attrs":[]},{"type":"domain","value":"foxsportssupports.com","attrs":[]},{"type":"domain","value":"foxsportsuniversity.com","attrs":[]},{"type":"domain","value":"foxsportsworld.com","attrs":[]},{"type":"domain","value":"foxstudiolot.com","attrs":[]},{"type":"domain","value":"foxsuper6.com","attrs":[]},{"type":"domain","value":"foxtel.com","attrs":[]},{"type":"domain","value":"foxtel.com.au","attrs":[]},{"type":"domain","value":"foxtelevisionstations.com","attrs":[]},{"type":"domain","value":"foxtv.com","attrs":[]},{"type":"domain","value":"foxtvdvd.com","attrs":[]},{"type":"domain","value":"foxuv.com","attrs":[]},{"type":"domain","value":"foxweatherwatch.com","attrs":[]},{"type":"domain","value":"fse.tv","attrs":[]},{"type":"domain","value":"fssta.com","attrs":[]},{"type":"domain","value":"fxn.ws","attrs":[]},{"type":"domain","value":"fxnetwork.com","attrs":[]},{"type":"domain","value":"fxnetworks.com","attrs":[]},{"type":"domain","value":"geraldoatlarge.com","attrs":[]},{"type":"domain","value":"gooddaychicago.com","attrs":[]},{"type":"domain","value":"joeswall.com","attrs":[]},{"type":"domain","value":"kicu.tv","attrs":[]},{"type":"domain","value":"kilmeadeandfriends.com","attrs":[]},{"type":"domain","value":"ktvu.com","attrs":[]},{"type":"domain","value":"maskedsingerfox.com","attrs":[]},{"type":"domain","value":"my13la.com","attrs":[]},{"type":"domain","value":"my20dc.com","attrs":[]},{"type":"domain","value":"my20houston.com","attrs":[]},{"type":"domain","value":"my29tv.com","attrs":[]},{"type":"domain","value":"my45.com","attrs":[]},{"type":"domain","value":"my9nj.com","attrs":[]},{"type":"domain","value":"myfoxatlanta.com","attrs":[]},{"type":"domain","value":"myfoxaustin.com","attrs":[]},{"type":"domain","value":"myfoxboston.com","attrs":[]},{"type":"domain","value":"myfoxcharlotte.com","attrs":[]},{"type":"domain","value":"myfoxchicago.com","attrs":[]},{"type":"domain","value":"myfoxdc.com","attrs":[]},{"type":"domain","value":"myfoxdetroit.com","attrs":[]},{"type":"domain","value":"myfoxdfw.com","attrs":[]},{"type":"domain","value":"myfoxhouston.com","attrs":[]},{"type":"domain","value":"myfoxhurricane.com","attrs":[]},{"type":"domain","value":"myfoxla.com","attrs":[]},{"type":"domain","value":"myfoxlosangeles.com","attrs":[]},{"type":"domain","value":"myfoxlubbock.com","attrs":[]},{"type":"domain","value":"myfoxmaine.com","attrs":[]},{"type":"domain","value":"myfoxny.com","attrs":[]},{"type":"domain","value":"myfoxorlando.com","attrs":[]},{"type":"domain","value":"myfoxphilly.com","attrs":[]},{"type":"domain","value":"myfoxphoenix.com","attrs":[]},{"type":"domain","value":"myfoxsanfran.com","attrs":[]},{"type":"domain","value":"myfoxtampa.com","attrs":[]},{"type":"domain","value":"myfoxtampabay.com","attrs":[]},{"type":"domain","value":"myfoxtwincities.com","attrs":[]},{"type":"domain","value":"myfoxzone.com","attrs":[]},{"type":"domain","value":"myq2.com","attrs":[]},{"type":"domain","value":"newsnowfox.com","attrs":[]},{"type":"domain","value":"orlandohurricane.com","attrs":[]},{"type":"domain","value":"paradisehotelquizfox.com","attrs":[]},{"type":"domain","value":"q13.com","attrs":[]},{"type":"domain","value":"q13fox.com","attrs":[]},{"type":"domain","value":"realamericanstories.com","attrs":[]},{"type":"domain","value":"realamericanstories.info","attrs":[]},{"type":"domain","value":"realamericanstories.net","attrs":[]},{"type":"domain","value":"realamericanstories.org","attrs":[]},{"type":"domain","value":"realamericanstories.tv","attrs":[]},{"type":"domain","value":"realmilwaukeenow.com","attrs":[]},{"type":"domain","value":"rprimelab.com","attrs":[]},{"type":"domain","value":"shopspeedtv.com","attrs":[]},{"type":"domain","value":"soccermatchpass.com","attrs":[]},{"type":"domain","value":"speeddreamride.com","attrs":[]},{"type":"domain","value":"speedfantasybid.com","attrs":[]},{"type":"domain","value":"speedracegear.com","attrs":[]},{"type":"domain","value":"speedxtra.com","attrs":[]},{"type":"domain","value":"teenchoice.com","attrs":[]},{"type":"domain","value":"testonfox.com","attrs":[]},{"type":"domain","value":"theclasshroom.com","attrs":[]},{"type":"domain","value":"thefoxnation.com","attrs":[]},{"type":"domain","value":"thegeorgiascene.com","attrs":[]},{"type":"domain","value":"tubi.io","attrs":[]},{"type":"domain","value":"tubi.tv","attrs":[]},{"type":"domain","value":"tubi.video","attrs":[]},{"type":"domain","value":"tubitv.com","attrs":[]},{"type":"domain","value":"whatthefox.com","attrs":[]},{"type":"domain","value":"whosthehost.com","attrs":[]},{"type":"domain","value":"wofl.tv","attrs":[]},{"type":"domain","value":"woflthenewsstation.com","attrs":[]},{"type":"domain","value":"wogx.com","attrs":[]},{"type":"full","value":"foxnewsplayer-a.akamaihd.net","attrs":[]}]}
