{"name":"SPOTIFY","rules":[{"type":"domain","value":"byspotify.com","attrs":[]},{"type":"domain","value":"pscdn.co","attrs":[]},{"type":"domain","value":"scdn.co","attrs":[]},{"type":"domain","value":"spoti.fi","attrs":[]},{"type":"domain","value":"spotify-everywhere.com","attrs":[]},{"type":"domain","value":"spotify.com","attrs":[]},{"type":"domain","value":"spotify.design","attrs":[]},{"type":"domain","value":"spotify.link","attrs":[]},{"type":"domain","value":"spotifycdn.com","attrs":[]},{"type":"domain","value":"spotifycdn.net","attrs":[]},{"type":"domain","value":"spotifycharts.com","attrs":[]},{"type":"domain","value":"spotifycodes.com","attrs":[]},{"type":"domain","value":"spotifyforbrands.com","attrs":[]},{"type":"domain","value":"spotifyjobs.com","attrs":[]},{"type":"full","value":"audio-ak-spotify-com.akamaized.net","attrs":[]},{"type":"full","value":"audio4-ak-spotify-com.akamaized.net","attrs":[]},{"type":"full","value":"cdn-spotify-experiments.conductrics.com","attrs":[]},{"type":"full","value":"heads-ak-spotify-com.akamaized.net","attrs":[]},{"type":"full","value":"heads4-ak-spotify-com.akamaized.net","attrs":[]},{"type":"full","value":"spotify.com.edgesuite.net","attrs":[]},{"type":"full","value":"spotify.map.fastly.net","attrs":[]},{"type":"full","value":"spotify.map.fastlylb.net","attrs":[]}]}
